Ast_Stubgen/__init__.py
Ast_Stubgen/stubgen.py
AST_Stubgen-0.1.5.dist-info/LICENSE
AST_Stubgen-0.1.5.dist-info/METADATA
AST_Stubgen-0.1.5.dist-info/WHEEL
AST_Stubgen-0.1.5.dist-info/top_level.txt
AST_Stubgen-0.1.5.dist-info/RECORD
